gnss_benchmark/__init__.py
gnss_benchmark/jason.py
gnss_benchmark/main.py
gnss_benchmark/report.py
gnss_benchmark/datasets/argonaut_single_static_16m_10Hz/PLAN00ESP_R_20202591000_02H_01S_MO.rnx
gnss_benchmark/datasets/argonaut_single_static_16m_10Hz/argonaut_1.rnx
gnss_benchmark/datasets/argonaut_single_static_16m_10Hz/description.json
gnss_benchmark/datasets/argonaut_single_static_3m_10Hz/PLAN00ESP_R_20202591000_02H_01S_MO.rnx
gnss_benchmark/datasets/argonaut_single_static_3m_10Hz/argonaut_2.rnx
gnss_benchmark/datasets/argonaut_single_static_3m_10Hz/description.json
gnss_benchmark/datasets/geodetic_multi_static_1h_1Hz/description.json
gnss_benchmark/datasets/geodetic_multi_static_1h_1Hz/mhdl100t.20o
gnss_benchmark/datasets/geodetic_multi_static_1h_1Hz/tibb100t.20o
gnss_benchmark/datasets/geodetic_multi_static_24h_30s/SBAR00ESP_R_20202020000_01D_30S_MO.rnx
gnss_benchmark/datasets/geodetic_multi_static_24h_30s/description.json
gnss_benchmark/datasets/geodetic_single_codeonly_static/description.json
gnss_benchmark/datasets/geodetic_single_codeonly_static/mhdl100t.20o_l1_code_only
gnss_benchmark/datasets/geodetic_single_static/description.json
gnss_benchmark/datasets/geodetic_single_static/mhdl100t.20o_l1
gnss_benchmark/datasets/geodetic_single_static/tibb100t.20o
gnss_benchmark/datasets/mosaicx5_multi_dynamic/CARD00ESP_R_20203340900_15H_MN.rnx
gnss_benchmark/datasets/mosaicx5_multi_dynamic/CARD00ESP_R_20203341240_20M_01S_MO.rnx
gnss_benchmark/datasets/mosaicx5_multi_dynamic/COD21340.sp3
gnss_benchmark/datasets/mosaicx5_multi_dynamic/MARE00ESP_R_20203341240_20M_01S_MO.rnx
gnss_benchmark/datasets/mosaicx5_multi_dynamic/description.json
gnss_benchmark/datasets/mosaicx5_multi_dynamic/igr21340.sp3
gnss_benchmark/datasets/mosaicx5_multi_dynamic/reference_trajectory.csv
gnss_benchmark/datasets/smartphone_single_static/BCL11400.obs
gnss_benchmark/datasets/smartphone_single_static/description.json
gnss_benchmark-2.3.0.dist-info/METADATA
gnss_benchmark-2.3.0.dist-info/WHEEL
gnss_benchmark-2.3.0.dist-info/entry_points.txt
gnss_benchmark-2.3.0.dist-info/top_level.txt
gnss_benchmark-2.3.0.dist-info/RECORD
