Metadata-Version: 2.1
Name: gnss-benchmark
Version: 2.3.0
Summary: GNSS benchmarking tool
Home-page: https://github.com/rokubun/gnss-benchmark
Author: Rokubun
Author-email: info@rokubun.cat
License: http://opensource.org/licenses/MIT
Platform: UNKNOWN
Requires-Dist: docopt
Requires-Dist: jason-gnss (>=1.10.0)
Requires-Dist: jinja2
Requires-Dist: matplotlib
Requires-Dist: numpy
Requires-Dist: pandoc
Requires-Dist: pyproj
Requires-Dist: pytest
Requires-Dist: requests
Requires-Dist: roktools
